ocean_events_handler/__init__.py
ocean_events_handler/config.py
ocean_events_handler/log.py
ocean_events_handler/provider_events_monitor.py
ocean_events_handler/util.py
ocean_events_handler/agreement_store/__init__.py
ocean_events_handler/agreement_store/agreements.py
ocean_events_handler/event_handlers/__init__.py
ocean_events_handler/event_handlers/accessSecretStore.py
ocean_events_handler/event_handlers/escrowRewardCondition.py
ocean_events_handler/event_handlers/lockRewardCondition.py
ocean_events_handler/event_handlers/lockRewardExecutionCondition.py
ocean_events_handler-0.4.7.dist-info/LICENSE
ocean_events_handler-0.4.7.dist-info/METADATA
ocean_events_handler-0.4.7.dist-info/WHEEL
ocean_events_handler-0.4.7.dist-info/top_level.txt
ocean_events_handler-0.4.7.dist-info/RECORD
