Metadata-Version: 2.1
Name: ocean-events-handler
Version: 0.4.7
Summary: 🐳 Publisher events handler agent dealing with Keeper Contract events.
Home-page: https://github.com/oceanprotocol/events-handler
Author: leucothia
Author-email: devops@oceanprotocol.com
License: Apache Software License 2.0
Keywords: ocean-events-handler
Platform: UNKNOWN
Classifier: Development Status :: 2 - Pre-Alpha
Classifier: Intended Audience :: Developers
Classifier: License :: OSI Approved :: Apache Software License
Classifier: Natural Language :: English
Classifier: Programming Language :: Python :: 3.6
Requires-Dist: ocean-utils (==0.3.5)
Requires-Dist: ocean-keeper (==0.3.5)
Requires-Dist: ocean-secret-store-client (==0.0.2)
Requires-Dist: PyYAML (==4.2b4)
Provides-Extra: dev
Requires-Dist: bumpversion ; extra == 'dev'
Requires-Dist: pkginfo ; extra == 'dev'
Requires-Dist: twine ; extra == 'dev'
Requires-Dist: watchdog ; extra == 'dev'
Requires-Dist: codacy-coverage ; extra == 'dev'
Requires-Dist: coverage ; extra == 'dev'
Requires-Dist: docker ; extra == 'dev'
Requires-Dist: mccabe ; extra == 'dev'
Requires-Dist: pylint ; extra == 'dev'
Requires-Dist: pytest ; extra == 'dev'
Requires-Dist: pytest-watch ; extra == 'dev'
Requires-Dist: tox ; extra == 'dev'
Requires-Dist: Sphinx ; extra == 'dev'
Requires-Dist: sphinxcontrib-apidoc ; extra == 'dev'
Provides-Extra: docs
Requires-Dist: Sphinx ; extra == 'docs'
Requires-Dist: sphinxcontrib-apidoc ; extra == 'docs'
Provides-Extra: test
Requires-Dist: codacy-coverage ; extra == 'test'
Requires-Dist: coverage ; extra == 'test'
Requires-Dist: docker ; extra == 'test'
Requires-Dist: mccabe ; extra == 'test'
Requires-Dist: pylint ; extra == 'test'
Requires-Dist: pytest ; extra == 'test'
Requires-Dist: pytest-watch ; extra == 'test'
Requires-Dist: tox ; extra == 'test'
